entry.py
accialcli-0.1.3.dist-info/entry_points.txt
accialcli-0.1.3.dist-info/WHEEL
accialcli-0.1.3.dist-info/METADATA
accialcli-0.1.3.dist-info/RECORD
