Metadata-Version: 2.1
Name: accialcli
Version: 0.1.3
Summary: CLI that send to our API 1 Borrower, 1 Application, 1 Loan and 1 Payment
Author: yud-cumba
Author-email: yudith.cumba@gmail.com
Requires-Python: >=3.8,<4.0
Classifier: Programming Language :: Python :: 3
Classifier: Programming Language :: Python :: 3.8
Classifier: Programming Language :: Python :: 3.9
Requires-Dist: click (>=8.0.1,<9.0.0)
Requires-Dist: requests (>=2.26.0,<3.0.0)
